[{"T":"301","2":"Lee","3":"The Industrial Carriage is right ahead of us."},{"T":"301","2":"Lee","3":"This has been going unexpectedly smoothly."},{"T":"301","2":"Liv","3":"All thanks to Sophia... I'm glad you're alright."},{"T":"301","2":"Liv","3":"You might be small in stature, but you're immensely capable..."},{"T":"301","2":"Lucia","3":"True!"},{"T":"301","2":"Sophia","3":"..."},{"T":"301","2":"Sophia","3":"The repair team will enter the carriage with you, then we'll split the group. The core of the manufacturing plant needs to be fixed immediately."},{"T":"301","2":"Lee","3":"I'll come with you, then."},{"T":"301","2":"Sophia","3":"(Nods)"},{"T":"301","2":"Lee","3":"The Industrial Carriage is filled with all kinds of machines, which means there will be quite a number of Corrupted."},{"T":"301","2":"Sophia","3":"You can take them down."},{"T":"301","2":"Lee","3":"In that case, Commandant, you'll lead the team to clear the Corrupted."},{"T":"301","2":"Sophia","3":"And the repair team will enter the plant to fix it up."},{"T":"302","2":"The Gray Ravens will support you.","4":"You two are quite in sync..."},{"T":"301","2":"Lucia","3":"I've optimized my frame's performance."},{"T":"301","2":"Lucia","3":"Liv, protect Commandant. I'll be in the front, trying to provide you with the most optimal operating environment. Bianca, you've got the rear. Don't let any Corrupted go."},{"T":"301","2":"Liv","3":"Roger!"},{"T":"301","2":"Bianca","3":"Understood."},{"T":"301","2":"Bianca","3":"...This feels like when I first joined the Purifying Force."},{"T":"301","2":"Lee","3":"I've sent you the blueprint of the carriage. The plan can't fully represent the actual environment, so you must be careful."},{"T":"301","2":"Lucia","3":"We will."},{"T":"301","2":"Liv","3":"You can count on me!"},{"T":"301","2":"Bianca","3":"Commandant, this will be a tough fight."},{"T":"302","2":"I'll be careful.","4":"When was I ever afraid?"},{"T":"301","2":"Bianca","3":"Don't worry, I'll also do my best to protect you."},{"T":"301","2":"Bianca","3":"I'm used to this kind of work, after all."},{"T":"301","2":"Bianca","3":"I believe in you."}]