[{"T":"301","2":"Nanami","3":"Ah, Nanami's all spent! I'm done playing!"},{"T":"301","2":"Rohacchi","3":"You. No. Fight. I. No. Fight."},{"T":"301","2":"Nanami","3":"Ehehe, I've been checking you out from the side. You seem different from the others, so I've been curious."},{"T":"301","2":"Nanami","3":"What's your name?"},{"T":"301","2":"Rohacchi","3":"Name. I. Name. Do. Not. Know."},{"T":"301","2":"Nanami","3":"You don't know your name? Lemme see, you have some numbers on your body, IX-68..."},{"T":"301","2":"Nanami","3":"Then Nanami will call you Rohacchi, fits just around Nanami!"},{"T":"301","2":"Rohacchi","3":"Roha. Chi. Nana. Mi?"},{"T":"301","2":"Nanami","3":"It's Rohacchi! It means six, eight and 'dachi'\u2014friend!"},{"T":"301","2":"Rohacchi","3":"Friend?"},{"T":"301","2":"Nanami","3":"Rohacchi and Nanami are best friends now!"},{"T":"301","2":"Rohacchi","3":"Friends. Companion. I. Like."},{"T":"301","2":"Nanami","3":"What are you doing here on yourself, Rohacchi?"},{"T":"301","2":"Rohacchi","3":"I. Find. Treasure. Mural. Sagemachina. Guidance."},{"T":"301","2":"Nanami","3":"You're finding something? Then Nanami will help you find it!"},{"T":"301","2":"Rohacchi","3":"Bad. Guys. Up. There. Nanami. Might. Hurt."},{"T":"301","2":"Nanami","3":"Bad guys? Then just yeet them all to space!"},{"T":"301","2":"Rohacchi","3":"Yeet?"},{"T":"301","2":"Nanami","3":"That means to send them all to infinity and beyond."},{"T":"301","2":"Rohacchi","3":"Infinity. Nice."},{"T":"301","2":"Nanami","3":"Let's go let's go. Nanami can't wait to see the treasure!"}]