[{"Id": "1", "ActionId": "42", "Type": "101", "BeginAnim": "AniZhuanchangEnd", "Params[1]": "Assets/Product/Texture/Image/BgStory/Bgstory91.png"}, {"Id": "2", "ActionId": "2", "Type": "401", "Params[1]": "1", "Params[2]": "10"}, {"Id": "3", "ActionId": "31", "Type": "201", "Params[1]": "1", "Params[2]": "1021001"}, {"Id": "4", "ActionId": "32", "Type": "201", "Params[1]": "2", "Params[2]": "1031001", "Params[4]": "-600"}, {"Id": "5", "ActionId": "33", "Type": "201", "Params[1]": "3", "Params[2]": "1011001", "Params[4]": "600"}, {"Id": "6", "ActionId": "43", "Type": "301", "BeginAnim": "DialogEnable", "Params[1]": "1", "Params[2]": "Lucia", "Params[3]": "Lee, the flanks!", "Params[4]": "1"}, {"Id": "7", "ActionId": "44", "Type": "301", "Params[1]": "1", "Params[2]": "Lee", "Params[3]": "Son of a\u2014they're all holed up in the corners!", "Params[4]": "3"}, {"Id": "8", "ActionId": "45", "Type": "301", "Params[1]": "1", "Params[2]": "Lee", "Params[3]": "We're cut off by the explosion. The only way is forward!", "Params[4]": "3"}, {"Id": "9", "ActionId": "46", "Type": "301", "Params[1]": "1", "Params[2]": "Liv", "Params[3]": "Mapping route now... No... There are too many Corrupted ahead!", "Params[4]": "2"}, {"Id": "10", "ActionId": "47", "Type": "202", "Params[1]": "1", "Params[2]": "2", "Params[3]": "3", "Params[6]": "1"}, {"Id": "11", "ActionId": "48", "Type": "301", "Params[2]": "???", "Params[3]": "\u2014\u2014WARNING, WARNING\u2014\u2014"}, {"Id": "12", "ActionId": "49", "Type": "301", "Params[2]": "???", "Params[3]": "\u2014\u2014Foreign object detected: Automated cleaning program will begin in 5 minutes\u2014\u2014"}, {"Id": "13", "ActionId": "50", "Type": "301", "Params[2]": "???", "Params[3]": "\u2014\u2014Workers should refrain from entering the conveyor sections to avoid potential injuries\u2014\u2014"}, {"Id": "14", "ActionId": "51", "Type": "201", "Params[1]": "1", "Params[2]": "1021001", "Params[4]": "-400", "Params[7]": "1"}, {"Id": "15", "ActionId": "52", "Type": "201", "Params[1]": "2", "Params[2]": "1011001", "Params[4]": "400", "Params[7]": "1"}, {"Id": "16", "ActionId": "53", "Type": "301", "Params[1]": "1", "Params[2]": "Lucia", "Params[3]": "What was that?", "Params[4]": "1"}, {"Id": "17", "ActionId": "54", "Type": "301", "Params[1]": "1", "Params[2]": "Lee", "Params[3]": "I can't be sure, but it sounds like something is coming in 5 minutes!", "Params[4]": "2"}, {"Id": "18", "ActionId": "55", "Type": "202", "Params[1]": "1", "Params[2]": "2", "Params[6]": "1"}, {"Id": "19", "ActionId": "56", "Type": "301", "Params[2]": "???", "Params[3]": "\u2014\u2014WARNING, WARNING\u2014\u2014"}, {"Id": "20", "ActionId": "57", "Type": "301", "Params[2]": "???", "Params[3]": "\u2014\u2014Automated cleaning program is now commencing\u2014\u2014"}, {"Id": "21", "ActionId": "58", "Type": "301", "Params[2]": "???", "Params[3]": "\u2014\u2014All workers should evacuate from the area: This is not a drill\u2014\u2014"}, {"Id": "22", "ActionId": "59", "Type": "201", "Params[1]": "1", "Params[2]": "1011001", "Params[3]": "21"}, {"Id": "23", "ActionId": "60", "Type": "301", "Params[1]": "1", "Params[2]": "Lee", "Params[3]": "Incoming! Duck!", "Params[4]": "1"}, {"Id": "24", "ActionId": "61", "Type": "202", "Params[1]": "1", "Params[6]": "1"}, {"Id": "25", "ActionId": "62", "Type": "301", "Params[3]": "A massive crane zooms past you and the others. Luckily, you all duck just in time."}, {"Id": "26", "ActionId": "63", "Type": "301", "Params[3]": "The Corrupted, however, were not so lucky. The crane knocks them all over."}, {"Id": "27", "ActionId": "64", "Type": "201", "Params[1]": "1", "Params[2]": "1021001", "Params[7]": "1"}, {"Id": "28", "ActionId": "65", "Type": "301", "Params[1]": "1", "Params[2]": "Lucia", "Params[3]": "Now!", "Params[4]": "1"}, {"Id": "29", "ActionId": "66", "Type": "202", "Params[1]": "1", "Params[6]": "1"}, {"Id": "30", "ActionId": "67", "Type": "301", "EndAnim": "AniZhuanchangBegin", "Params[3]": "With the Corrupted all immobilized from the impact, you quickly withdraw from the area. Some of their broken limbs splinter from your hurried sprint.", "Params[6]": "1"}, {"Id": "31", "ActionId": "68", "Type": "301", "BeginAnim": "AniZhuanchangEnd", "Params[2]": "???", "Params[3]": "\u2014\u2014Foreign objects stabilized: Commencing annihilative purge program\u2014\u2014", "Params[6]": "1"}, {"Id": "32", "ActionId": "69", "Type": "301", "Params[3]": "The high acidity reagent and pressurized freezing reagent take turns mowing down the already crushed Corrupted, until all that was left was corroded, flash-frozen slag."}, {"Id": "33", "ActionId": "70", "Type": "301", "Params[3]": "And finally, a final discharge of pressurized water sends the Corrupted to their final respite\u2014the sea."}, {"Id": "34", "ActionId": "71", "Type": "201", "Params[1]": "1", "Params[2]": "1021001"}, {"Id": "35", "ActionId": "72", "Type": "201", "Params[1]": "2", "Params[2]": "1031001", "Params[4]": "-600"}, {"Id": "36", "ActionId": "73", "Type": "201", "Params[1]": "3", "Params[2]": "1011001", "Params[4]": "600"}, {"Id": "37", "ActionId": "74", "Type": "301", "Params[1]": "1", "Params[2]": "Liv", "Params[3]": "What... was... that...?", "Params[4]": "2"}, {"Id": "38", "ActionId": "75", "Type": "301", "Params[1]": "1", "Params[2]": "Lee", "Params[3]": "Whole sets of cranes, conveyor belt routing, and a cooling function... That's the full course. Looks like the logistic systems are still online.", "Params[4]": "3"}, {"Id": "39", "ActionId": "76", "Type": "301", "Params[1]": "1", "Params[2]": "Lee", "Params[3]": "The central AI must have repurposed the freight systems to deal with the Corrupted nearby...", "Params[4]": "3"}, {"Id": "40", "ActionId": "77", "Type": "301", "Params[1]": "1", "Params[2]": "Lucia", "Params[3]": "That must be why we see so few Corrupted the closer we get to the center.", "Params[4]": "1"}, {"Id": "41", "ActionId": "78", "Type": "301", "Params[1]": "1", "Params[2]": "Lucia", "Params[3]": "Normal Corrupted would never survive this.", "Params[4]": "1"}, {"Id": "42", "ActionId": "79", "Type": "301", "Params[1]": "1", "Params[2]": "Lee", "Params[3]": "Yep, that should be the case.", "Params[4]": "3"}, {"Id": "43", "ActionId": "80", "Type": "301", "Params[1]": "1", "Params[2]": "Lee", "Params[3]": "Let's try to head to the purification filter now that most of the Corrupted are gone.", "Params[4]": "3"}, {"Id": "44", "ActionId": "81", "Type": "301", "Params[1]": "1", "Params[2]": "Lee", "Params[3]": "If the sensors aren't lying, then the CPF should be near the center of the hub.", "Params[4]": "3"}, {"Id": "45", "ActionId": "82", "Type": "302", "Params[2]": "Let's go, then.", "Params[3]": "83"}, {"Id": "46", "ActionId": "83", "Type": "301", "IsEnd": "1", "EndAnim": "AniZhuanchangBegin", "Params[1]": "1", "Params[2]": "Gray Raven", "Params[3]": "Understood.", "Params[4]": "1", "Params[5]": "2", "Params[6]": "3"}]