[{"T":"301","2":"\u03b1","3":"Sorry. Must have woke you up."},{"T":"301","3":"Finished with the skirmish, Alpha returns to the bench to find Luna long awake. Luna merely shakes her head at Alpha's apology."},{"T":"301","2":"Luna","3":"It's okay."},{"T":"301","2":"\u03b1","3":"What's the matter? You're staring at me."},{"T":"301","2":"Luna","3":"Ahaha... Nothing. It really fits you."},{"T":"301","2":"\u03b1","3":"Yeah. The texture is nice. I think it's some famous brand from the Golden Age. The design makes swinging my sword easy."},{"T":"301","2":"Luna","3":"That's not what I meant by fitting you."},{"T":"301","3":"Luna's words send Alpha into deep thought. Then suddenly, as if in realization, she opens her mouth and continues."},{"T":"301","2":"\u03b1","3":"Well... Next time, if you want pictures of me, just say so. You don't have to take them secretly."},{"T":"301","2":"Luna","3":"That won't be the same."},{"T":"301","2":"\u03b1","3":"...I guess."},{"T":"301","2":"Luna","3":"Well, it's late. Let's go back."},{"T":"301","3":"Luna rises from the bench and puts a jacket on Alpha, then turns and saunters through the road they came from."},{"T":"301","2":"\u03b1","3":"Sure."},{"T":"301","3":"Alpha nods, and falls in step with Luna after accepting her jacket."},{"T":"301","3":"After Luna and Alpha left, a figure emerges from the shadows of the walkway."},{"T":"301","3":"He gazes in the direction of the two and falls into deep thought."},{"T":"301","2":"Roland","3":"..."}]