[{"T":"301","2":"Nanny","3":"Found you!"},{"T":"301","2":"Nanny","3":"It's you...!"},{"T":"301","3":"The nanny rushes toward the bawling child, while in the shadows, a sharp blade flashes into sight\u2014"},{"T":"301","2":"???","3":"No... My baby!"},{"T":"301","2":"'Child'","3":"You! You killed my mommy! Go away!"},{"T":"301","3":"A malicious glint flashes in the darkness, and the child rams a knife into the nanny's form. Her metal shell crumbles, vital fluid flooding out."},{"T":"301","3":"The lights come on to reveal the caretaker's form, curled up tight around the child, knife in her abdomen. On her torso rests the weapon aimed at the child, plunged deep into her own body."},{"T":"301","2":"Bianca","3":"...! Punishing Virus levels surging in the caretaker android."},{"T":"301","2":"Lucia","3":"It's drawing the Corrupted in."},{"T":"301","2":"Kamui","3":"Damn it!"},{"T":"301","2":"Bianca","3":"I took care of some of those with my arrows."},{"T":"301","3":"Neutralize all hostiles!"},{"T":"301","2":"Everyone","3":"Roger!"}]