[{"T":"301","3":"Disconnecting the cable, Nanami's face is veiled behind her upraised arm."},{"T":"301","3":"And so, Martin and Rohacchi do not catch her saddened expression."},{"T":"301","2":"Nanami","3":"Phew..."},{"T":"301","2":"Martin","3":"What happened? You just went silent, so we didn't feel safe disconnecting you from the terminal."},{"T":"301","2":"Rohacchi","3":"Test. Not?"},{"T":"301","2":"Nanami","3":"Oh, um... Haha, that mecha babushka just barged in immediately."},{"T":"301","2":"Nanami","3":"But it's okay, it told me everything it wanted to."},{"T":"301","2":"Rohacchi","3":"Now. What. Do?"},{"T":"301","2":"Nanami","3":"Now... Let's see..."},{"T":"301","2":"Nanami","3":"Oh, right! In that book, the protagonist has three other companions!"},{"T":"301","2":"Nanami","3":"But here, we only have... two. So, next up, let's look for the third!"},{"T":"301","2":"Martin & Rohacchi","3":"...?"}]