[{"T":"301","2":"Liv","3":"I've selected the appropriate program based on the criteria."},{"T":"302","2":"From your previous questions?","4":"What kind of training is it?"},{"T":"301","2":"Liv","3":"That's right. It's more effective choosing this way."},{"T":"301","2":"Liv","3":"What we'll be doing today is the first step of the training program\u2014thinking exercise."},{"T":"302","2":"Thinking exercise?","4":"It sounds very philosophical."},{"T":"301","2":"Liv","3":"It's just a name. The training itself is still fairly practical."},{"T":"301","2":"Liv","3":"Despite its name, what we're actually working on is tactical thinking as well as improvisational skills."},{"T":"301","2":"Liv","3":"Many different circumstances during battles could cause us to disconnect from you, Commandant."},{"T":"301","2":"Liv","3":"Which means the duty to continue our mission and protect ourselves would lie on us."},{"T":"301","2":"Liv","3":"Unlike Lucia and Lee, I'm not very skilled in this aspect."},{"T":"301","2":"Liv","3":"Sometimes I'd even misjudge the situation like when I opened fire last time... If only I..."},{"T":"302","2":"Don't get brought down by what happened.","4":"I should have given you instructions as well."},{"T":"301","2":"Liv","3":"As Constructs, we are not allowed to fail."},{"T":"301","2":"Liv","3":"It wasn't your fault, Commandant. I was weak."},{"T":"301","2":"Liv","3":"Regardless, all you have to do during the training is to come up with the problems and grade me on how I act, Commandant."},{"T":"301","2":"Liv","3":"I'll get through whatever obstacles that come up myself... Commandant, please just stand aside and watch."},{"T":"302","2":"Will do.","4":"Are you sure?"},{"T":"301","2":"Liv","3":"Let's begin!"},{"T":"301","2":"Liv","3":"I am! I'll do my best!"}]