[{"T":"301","3":"The three of them set out before dawn."},{"T":"301","2":"HBG3","3":"We are getting closer and closer to the war zone."},{"T":"301","3":"The ground still remains hot from the battle, making their journey arduous as they climb over the ruins."},{"T":"301","2":"Little Girl","3":"Ah...!"},{"T":"301","3":"The girl lets out a small surprised scream at a piles of bodies nearby, but then quiets down shortly."},{"T":"301","2":"HNB1","3":"Just up ahead, and we're there."},{"T":"301","2":"Unknown Corrupted","3":"(Rustling noises)"},{"T":"301","3":"A mechanical monster jumps down from a tall building and roars, alerting more machines to come out from the surroundings."},{"T":"301","2":"HNB1","3":"Tell me you have a backup plan."},{"T":"301","2":"HBG3","3":"The backup plan is\u2014get behind me!"}]